esp32_micropython/__init__.py
esp32_micropython/dm.py
esp32_micropython-0.2.6.dist-info/licenses/LICENSE
esp32_micropython-0.2.6.dist-info/METADATA
esp32_micropython-0.2.6.dist-info/WHEEL
esp32_micropython-0.2.6.dist-info/entry_points.txt
esp32_micropython-0.2.6.dist-info/top_level.txt
esp32_micropython-0.2.6.dist-info/RECORD
