Metadata-Version: 2.4
Name: esp32-micropython
Version: 0.2.6
Summary: All-in-one utility for flashing and managing MicroPython deployments on ESP32-C3 SuperMini boards.
Author-email: "aistack.pl" <lael@aistack.pl>
Maintainer-email: "aistack.pl" <lael@aistack.pl>
License-Expression: MIT
Project-URL: Homepage, https://laelhalawani.github.io/esp32_micropython/
Project-URL: Repository, https://github.com/aistack-pl/esp32-micropython
Project-URL: Bug_Tracker, https://github.com/aistack-pl/esp32-micropython/issues
Keywords: esp32,esp32-c3,micropython,flash,deploy,mpremote,esptool,firmware
Classifier: Development Status :: 4 - Beta
Classifier: Intended Audience :: Developers
Classifier: Topic :: Software Development :: Embedded Systems
Classifier: Topic :: System :: Hardware :: Hardware Drivers
Classifier: Topic :: Terminals :: Serial
Classifier: Topic :: Utilities
Classifier: Programming Language :: Python :: 3
Classifier: Programming Language :: Python :: 3.11
Classifier: Operating System :: OS Independent
Classifier: Environment :: Console
Requires-Python: <3.12,>=3.11
License-File: LICENSE
Requires-Dist: esptool==4.8.1
Requires-Dist: mpremote==1.25.0
Requires-Dist: micropython-esp32-stubs==1.25.0.post2
Requires-Dist: micropython-esp32-esp32_generic_c3-stubs==1.23.0.post2
Dynamic: license-file
